pyremsql/__init__.py
pyremsql-0.0.1.dist-info/METADATA
pyremsql-0.0.1.dist-info/WHEEL
pyremsql-0.0.1.dist-info/top_level.txt
pyremsql-0.0.1.dist-info/RECORD
