Metadata-Version: 2.1
Name: pyremsql
Version: 0.0.1
Summary: Python wrapper for RemoteSQLite API
Home-page: https://github.com/XazkerBoy/RemoteSQLite
Author: Xazker
Author-email: xazkerboy@gmail.com
License: GPL3
Platform: UNKNOWN
Requires-Python: >=3.6, <4
Requires-Dist: requests (>=2.25.0)
